<?xml version="1.0"?>
<opencv_storage>
<stage20>
  <maxWeakCount>8</maxWeakCount>
  <stageThreshold>-4.7592714428901672e-01</stageThreshold>
  <weakClassifiers>
    <_>
      <internalNodes>
        0 -1 35009 -1.0382663458585739e-02</internalNodes>
      <leafValues>
        1. -1.5030674636363983e-01</leafValues></_>
    <_>
      <internalNodes>
        0 -1 69412 9.7397854551672935e-04</internalNodes>
      <leafValues>
        -1.7729106545448303e-01 1.</leafValues></_>
    <_>
      <internalNodes>
        0 -1 15358 -1.0679095983505249e-01</internalNodes>
      <leafValues>
        1. -1.5273860096931458e-01</leafValues></_>
    <_>
      <internalNodes>
        0 -1 45110 -1.7629625508561730e-03</internalNodes>
      <leafValues>
        7.3352247476577759e-01 -3.2009032368659973e-01</leafValues></_>
    <_>
      <internalNodes>
        0 -1 23178 3.0782055546296760e-05</internalNodes>
      <leafValues>
        -3.5182815790176392e-01 7.5514423847198486e-01</leafValues></_>
    <_>
      <internalNodes>
        0 -1 42990 2.8079347684979439e-03</internalNodes>
      <leafValues>
        8.7071228027343750e-01 -2.6498517394065857e-01</leafValues></_>
    <_>
      <internalNodes>
        0 -1 38848 2.1847434341907501e-02</internalNodes>
      <leafValues>
        5.0057464838027954e-01 -6.4369815587997437e-01</leafValues></_>
    <_>
      <internalNodes>
        0 -1 19705 -3.9418078958988190e-03</internalNodes>
      <leafValues>
        -5.5261451005935669e-01 5.3139823675155640e-01</leafValues></_></weakClassifiers></stage20>
</opencv_storage>
